LICENSE
MANIFEST.in
README.rst
setup.py
pinyin/Mandarin.dat
pinyin/__init__.py
pinyin/_compat.py
pinyin/cmd.py
pinyin/pinyin.py
pinyin.egg-info/PKG-INFO
pinyin.egg-info/SOURCES.txt
pinyin.egg-info/dependency_links.txt
pinyin.egg-info/entry_points.txt
pinyin.egg-info/top_level.txt