Metadata-Version: 1.1
Name: pinyin
Version: 0.3
Summary: Translate chinese chars to pinyin based on Mandarin.dat
Home-page: http://lxyu.github.io/pinyin/
Author: Lx Yu
Author-email: github@lxyu.net
License: BSD
Platform: UNKNOWN
Classifier: Topic :: Software Development
Classifier: Development Status :: 4 - Beta
Classifier: Intended Audience :: Developers
Classifier: License :: OSI Approved :: BSD License
Classifier: Programming Language :: Python :: 2.6
Classifier: Programming Language :: Python :: 2.7
Classifier: Programming Language :: Python :: 3.2
Classifier: Programming Language :: Python :: 3.3
Classifier: Programming Language :: Python :: 3.4
Classifier: Programming Language :: Python :: 3.5
Classifier: Programming Language :: Python :: Implementation :: CPython
Classifier: Programming Language :: Python :: Implementation :: PyPy
